ssm/__init__.py
ssm/__main__.py
ssm/aws.py
ssm/cli.py
ssm/utils.py
ssm_loader-0.2.4.dist-info/LICENSE
ssm_loader-0.2.4.dist-info/METADATA
ssm_loader-0.2.4.dist-info/WHEEL
ssm_loader-0.2.4.dist-info/entry_points.txt
ssm_loader-0.2.4.dist-info/top_level.txt
ssm_loader-0.2.4.dist-info/RECORD
