Metadata-Version: 2.1
Name: ssm-loader
Version: 0.2.4
Summary: Python app to load SSM
Home-page: UNKNOWN
Author: DNX Solutions
Author-email: contact@dnx.solutions
License: UNKNOWN
Platform: UNKNOWN
Classifier: Development Status :: 5 - Production/Stable
Classifier: Intended Audience :: Developers
Classifier: Intended Audience :: System Administrators
Classifier: Natural Language :: English
Classifier: License :: OSI Approved :: Apache Software License
Classifier: Programming Language :: Python
Classifier: Programming Language :: Python :: 3
Classifier: Programming Language :: Python :: 3.4
Classifier: Programming Language :: Python :: 3.5
Classifier: Programming Language :: Python :: 3.6
Classifier: Programming Language :: Python :: 3.7
Classifier: Programming Language :: Python :: 3.8
Requires-Python: >=3.6
Requires-Dist: awscli (==1.18.111)
Requires-Dist: boto3 (==1.14.34)
Requires-Dist: click (==7.1.2)
Provides-Extra: build
Requires-Dist: twine ; extra == 'build'
Requires-Dist: setuptools ; extra == 'build'
Requires-Dist: wheel ; extra == 'build'
Provides-Extra: test
Requires-Dist: moto (==1.3.13) ; extra == 'test'
Requires-Dist: pytest (==6.0.1) ; extra == 'test'
Requires-Dist: pytest-cov (==2.10.0) ; extra == 'test'
Requires-Dist: flake8 (==3.8.3) ; extra == 'test'
